README.md
setup.py
src/blackbook/__init__.py
src/blackbook/__main__.py
src/blackbook/version.py
src/blackbook.egg-info/PKG-INFO
src/blackbook.egg-info/SOURCES.txt
src/blackbook.egg-info/dependency_links.txt
src/blackbook.egg-info/entry_points.txt
src/blackbook.egg-info/requires.txt
src/blackbook.egg-info/top_level.txt