Metadata-Version: 1.0
Name: blackbook
Version: 0.0.4
Summary: `Black` for Jupyter notebooks.
Home-page: UNKNOWN
Author: Nikoleta Glynatsi, Vince Knight, Henry Wilde
Author-email: glynatsine@cardiff.ac.uk
License: The MIT License (MIT)
Platform: UNKNOWN
